[
  {
    "name": "The Willow Cafe",
    "category": "Bistro",
    "rating": 4.4,
    "reviews": 2450,
    "address": "Shop No. 1, Sector 10D, Sector 10",
    "area": "Sector 10",
    "city": "Chandigarh",
    "website": "Y",
    "phone": "+91 172 462 2333",
    "latitude": 30.7512,
    "longitude": 76.7901,
    "hours": "8:30 AM - 11:30 PM"
  },
  {
    "name": "Backpacker's Cafe",
    "category": "Bistro",
    "rating": 4.5,
    "reviews": 1890,
    "address": "SCF 16, Sector 9D, Sector 9",
    "area": "Sector 9",
    "city": "Chandigarh",
    "website": "N",
    "phone": "+91 172 400 3045",
    "latitude": 30.7455,
    "longitude": 76.7944,
    "hours": "8:30 AM - Midnight"
  },
  {
    "name": "Nik Baker's Sector 35",
    "category": "Bakery Cafe",
    "rating": 4.3,
    "reviews": 4120,
    "address": "SCO 441-442, Sector 35C, Sector 35",
    "area": "Sector 35",
    "city": "Chandigarh",
    "website": "Y",
    "phone": "+91 172 506 2233",
    "latitude": 30.7224,
    "longitude": 76.7681,
    "hours": "8:00 AM - 11:00 PM"
  },
  {
    "name": "Gopal's Sweets & Cafe",
    "category": "Traditional Cafe",
    "rating": 4.1,
    "reviews": 5600,
    "address": "SCO 459-460, Sector 35C, Sector 35",
    "area": "Sector 35",
    "city": "Chandigarh",
    "website": "Y",
    "phone": "+91 172 260 2311",
    "latitude": 30.723,
    "longitude": 76.7688,
    "hours": "9:00 AM - 10:30 PM"
  },
  {
    "name": "Indian Coffee House 17",
    "category": "Traditional Cafe",
    "rating": 4.0,
    "reviews": 6700,
    "address": "SCO 12, Sector 17E, Sector 17",
    "area": "Sector 17",
    "city": "Chandigarh",
    "website": "N",
    "phone": "+91 172 270 2133",
    "latitude": 30.7411,
    "longitude": 76.7824,
    "hours": "8:00 AM - 10:00 PM"
  },
  {
    "name": "Cafe JC's",
    "category": "Bistro",
    "rating": 4.4,
    "reviews": 1980,
    "address": "Coal Depot Complex, Sector 10D, Sector 10",
    "area": "Sector 10",
    "city": "Chandigarh",
    "website": "Y",
    "phone": "+91 172 463 3333",
    "latitude": 30.7518,
    "longitude": 76.7905,
    "hours": "10:00 AM - 11:30 PM"
  },
  {
    "name": "Uncle Jack's Sector 8",
    "category": "Dessert Cafe",
    "rating": 4.2,
    "reviews": 950,
    "address": "SCO 11, Sector 8B, Sector 8",
    "area": "Sector 8",
    "city": "Chandigarh",
    "website": "N",
    "phone": "+91 172 464 4444",
    "latitude": 30.7482,
    "longitude": 76.7981,
    "hours": "10:00 AM - 10:30 PM"
  },
  {
    "name": "The Hedgehog Cafe",
    "category": "Book Cafe",
    "rating": 4.3,
    "reviews": 820,
    "address": "SCF 12, Sector 21C, Sector 21",
    "area": "Sector 21",
    "city": "Chandigarh",
    "website": "N",
    "phone": "+91 172 465 5555",
    "latitude": 30.7321,
    "longitude": 76.7794,
    "hours": "9:00 AM - 11:00 PM"
  },
  {
    "name": "Brooklyn Central",
    "category": "Fine Dining Cafe",
    "rating": 4.2,
    "reviews": 1540,
    "address": "Elante Mall, Phase 1, Industrial Area",
    "area": "Elante Mall",
    "city": "Chandigarh",
    "website": "Y",
    "phone": "+91 172 466 6666",
    "latitude": 30.7058,
    "longitude": 76.8011,
    "hours": "11:00 AM - Midnight"
  },
  {
    "name": "Cafe Nomads",
    "category": "Bistro",
    "rating": 4.5,
    "reviews": 1100,
    "address": "SCO 120, Sector 7C, Sector 7",
    "area": "Sector 7",
    "city": "Chandigarh",
    "website": "N",
    "phone": "+91 172 467 7777",
    "latitude": 30.7431,
    "longitude": 76.8014,
    "hours": "9:00 AM - 11:30 PM"
  },
  {
    "name": "The Brew Room",
    "category": "Coffee Shop",
    "rating": 4.3,
    "reviews": 1250,
    "address": "SCO 14, Sector 9D, Sector 9",
    "area": "Sector 9",
    "city": "Chandigarh",
    "website": "Y",
    "phone": "+91 172 468 8888",
    "latitude": 30.7458,
    "longitude": 76.7938,
    "hours": "9:00 AM - 11:00 PM"
  },
  {
    "name": "Keventers Sector 35",
    "category": "Dessert Cafe",
    "rating": 4.1,
    "reviews": 680,
    "address": "SCO 431, Sector 35C, Sector 35",
    "area": "Sector 35",
    "city": "Chandigarh",
    "website": "N",
    "phone": "",
    "latitude": 30.7221,
    "longitude": 76.7679,
    "hours": "10:00 AM - Midnight"
  },
  {
    "name": "Garg Pastry Shop",
    "category": "Bakery Cafe",
    "rating": 3.9,
    "reviews": 230,
    "address": "Sector 22D, Sector 22",
    "area": "Sector 22",
    "city": "Chandigarh",
    "website": "N",
    "phone": "+91 172 272 1211",
    "latitude": 30.7388,
    "longitude": 76.7712,
    "hours": "9:00 AM - 10:00 PM"
  },
  {
    "name": "Sector 7 Social",
    "category": "Bistro",
    "rating": 4.4,
    "reviews": 4890,
    "address": "SCO 37, Sector 7C, Sector 7",
    "area": "Sector 7",
    "city": "Chandigarh",
    "website": "Y",
    "phone": "+91 172 473 3333",
    "latitude": 30.7428,
    "longitude": 76.801,
    "hours": "11:00 AM - 1:00 AM"
  },
  {
    "name": "Blue Tokai Coffee Roasters",
    "category": "Coffee Shop",
    "rating": 4.6,
    "reviews": 1150,
    "address": "SCO 14, Sector 8B, Sector 8",
    "area": "Sector 8",
    "city": "Chandigarh",
    "website": "Y",
    "phone": "+91 172 475 5555",
    "latitude": 30.7485,
    "longitude": 76.7984,
    "hours": "7:30 AM - 11:00 PM"
  },
  {
    "name": "Third Wave Coffee 35",
    "category": "Coffee Shop",
    "rating": 4.5,
    "reviews": 850,
    "address": "SCO 443, Sector 35C, Sector 35",
    "area": "Sector 35",
    "city": "Chandigarh",
    "website": "Y",
    "phone": "+91 172 476 6666",
    "latitude": 30.7225,
    "longitude": 76.7682,
    "hours": "8:00 AM - 11:30 PM"
  },
  {
    "name": "The Coffee Bean & Tea Leaf",
    "category": "Coffee Shop",
    "rating": 4.3,
    "reviews": 1420,
    "address": "Hotel Mountview, Sector 10",
    "area": "Sector 10",
    "city": "Chandigarh",
    "website": "Y",
    "phone": "+91 172 274 0544",
    "latitude": 30.7538,
    "longitude": 76.7915,
    "hours": "24 Hours"
  },
  {
    "name": "Scafe Cafe & Bistro",
    "category": "Bistro",
    "rating": 4.2,
    "reviews": 310,
    "address": "SCO 112, Sector 34C, Sector 34",
    "area": "Sector 34",
    "city": "Chandigarh",
    "website": "N",
    "phone": "+91 172 478 8888",
    "latitude": 30.7188,
    "longitude": 76.7612,
    "hours": "11:00 AM - 11:00 PM"
  },
  {
    "name": "Aroma Bakery & Cafe",
    "category": "Bakery Cafe",
    "rating": 4.1,
    "reviews": 3120,
    "address": "Hotel Aroma, Sector 22C, Sector 22",
    "area": "Sector 22",
    "city": "Chandigarh",
    "website": "Y",
    "phone": "+91 172 401 0000",
    "latitude": 30.735,
    "longitude": 76.7725,
    "hours": "24 Hours"
  },
  {
    "name": "Coffee Bistro Phase 3B2",
    "category": "Bistro",
    "rating": 4.4,
    "reviews": 1250,
    "address": "SCF 41, Phase 3B2",
    "area": "Phase 3B2",
    "city": "Mohali",
    "website": "N",
    "phone": "+91 172 481 1111",
    "latitude": 30.7042,
    "longitude": 76.7231,
    "hours": "10:00 AM - 11:30 PM"
  },
  {
    "name": "Nik Baker's Mohali",
    "category": "Bakery Cafe",
    "rating": 4.4,
    "reviews": 2890,
    "address": "SCF 54, Phase 3B2",
    "area": "Phase 3B2",
    "city": "Mohali",
    "website": "Y",
    "phone": "+91 172 506 3344",
    "latitude": 30.7048,
    "longitude": 76.7235,
    "hours": "8:00 AM - 11:00 PM"
  },
  {
    "name": "The Big Bro Mohali",
    "category": "Bistro",
    "rating": 4.2,
    "reviews": 1750,
    "address": "SCO 22, Phase 5",
    "area": "Phase 5",
    "city": "Mohali",
    "website": "N",
    "phone": "+91 172 482 2222",
    "latitude": 30.7088,
    "longitude": 76.7212,
    "hours": "11:00 AM - 11:00 PM"
  },
  {
    "name": "The Crown Patisserie",
    "category": "Bakery Cafe",
    "rating": 4.3,
    "reviews": 620,
    "address": "SCO 14, Phase 7",
    "area": "Phase 7",
    "city": "Mohali",
    "website": "N",
    "phone": "+91 172 483 3333",
    "latitude": 30.6975,
    "longitude": 76.7288,
    "hours": "11:00 AM - 10:30 PM"
  },
  {
    "name": "Brewbakes Cafe Mohali",
    "category": "Coffee Shop",
    "rating": 4.0,
    "reviews": 410,
    "address": "SCO 42, Sector 62, Phase 7",
    "area": "Phase 7",
    "city": "Mohali",
    "website": "Y",
    "phone": "",
    "latitude": 30.6981,
    "longitude": 76.7292,
    "hours": "10:30 AM - 11:00 PM"
  },
  {
    "name": "Cafe Mocha Mohali",
    "category": "Bistro",
    "rating": 4.2,
    "reviews": 1420,
    "address": "SCF 33, Phase 3B2",
    "area": "Phase 3B2",
    "city": "Mohali",
    "website": "Y",
    "phone": "+91 172 485 5555",
    "latitude": 30.7039,
    "longitude": 76.7228,
    "hours": "11:00 AM - Midnight"
  },
  {
    "name": "Amrit Sweets & Cafe",
    "category": "Traditional Cafe",
    "rating": 4.1,
    "reviews": 6800,
    "address": "SCO 56, Phase 5",
    "area": "Phase 5",
    "city": "Mohali",
    "website": "Y",
    "phone": "+91 172 222 1530",
    "latitude": 30.7092,
    "longitude": 76.7215,
    "hours": "8:30 AM - 10:30 PM"
  },
  {
    "name": "Katani Sweets Sector 70",
    "category": "Traditional Cafe",
    "rating": 3.9,
    "reviews": 4300,
    "address": "SCO 14, Sector 70",
    "area": "Sector 70",
    "city": "Mohali",
    "website": "N",
    "phone": "+91 172 486 6666",
    "latitude": 30.6908,
    "longitude": 76.7112,
    "hours": "8:00 AM - 10:30 PM"
  },
  {
    "name": "Whip Bakery",
    "category": "Bakery Cafe",
    "rating": 4.2,
    "reviews": 150,
    "address": "Phase 11, Sector 65",
    "area": "Phase 11",
    "city": "Mohali",
    "website": "N",
    "phone": "+91 172 487 7777",
    "latitude": 30.6688,
    "longitude": 76.7412,
    "hours": "10:00 AM - 10:00 PM"
  },
  {
    "name": "Starbucks Elante",
    "category": "Coffee Shop",
    "rating": 4.4,
    "reviews": 3200,
    "address": "Elante Mall, Phase 1, Industrial Area",
    "area": "Elante Mall",
    "city": "Chandigarh",
    "website": "Y",
    "phone": "+91 172 488 8888",
    "latitude": 30.7055,
    "longitude": 76.8015,
    "hours": "9:00 AM - Midnight"
  },
  {
    "name": "Starbucks Sector 35",
    "category": "Coffee Shop",
    "rating": 4.4,
    "reviews": 1850,
    "address": "SCO 447, Sector 35C, Sector 35",
    "area": "Sector 35",
    "city": "Chandigarh",
    "website": "Y",
    "phone": "+91 172 489 9999",
    "latitude": 30.7228,
    "longitude": 76.7685,
    "hours": "9:00 AM - 11:30 PM"
  },
  {
    "name": "Third Wave Coffee Mohali",
    "category": "Coffee Shop",
    "rating": 4.5,
    "reviews": 630,
    "address": "SCO 11, Phase 3B2",
    "area": "Phase 3B2",
    "city": "Mohali",
    "website": "Y",
    "phone": "+91 172 490 1111",
    "latitude": 30.7035,
    "longitude": 76.7225,
    "hours": "8:00 AM - 11:30 PM"
  },
  {
    "name": "Gullu's Coffee Corner",
    "category": "Coffee Shop",
    "rating": 4.5,
    "reviews": 410,
    "address": "Sector 15 Patel Market",
    "area": "Sector 15",
    "city": "Chandigarh",
    "website": "N",
    "phone": "",
    "latitude": 30.7512,
    "longitude": 76.7654,
    "hours": "11:00 AM - 10:00 PM"
  },
  {
    "name": "Stu-C Panjab University",
    "category": "Traditional Cafe",
    "rating": 4.3,
    "reviews": 9500,
    "address": "Panjab University, Sector 14",
    "area": "Sector 14",
    "city": "Chandigarh",
    "website": "N",
    "phone": "",
    "latitude": 30.7612,
    "longitude": 76.7688,
    "hours": "8:00 AM - 9:00 PM"
  },
  {
    "name": "The Chocolate Room Sector 7",
    "category": "Dessert Cafe",
    "rating": 4.1,
    "reviews": 520,
    "address": "SCO 12, Sector 7C, Sector 7",
    "area": "Sector 7",
    "city": "Chandigarh",
    "website": "Y",
    "phone": "+91 172 491 2222",
    "latitude": 30.7425,
    "longitude": 76.8005,
    "hours": "11:00 AM - 11:00 PM"
  },
  {
    "name": "Barista Sector 17",
    "category": "Coffee Shop",
    "rating": 4.2,
    "reviews": 850,
    "address": "SCO 55, Sector 17D, Sector 17",
    "area": "Sector 17",
    "city": "Chandigarh",
    "website": "Y",
    "phone": "+91 172 492 3333",
    "latitude": 30.7408,
    "longitude": 76.7818,
    "hours": "9:00 AM - 11:00 PM"
  },
  {
    "name": "Backyard Cafe & Bistro",
    "category": "Bistro",
    "rating": 4.3,
    "reviews": 290,
    "address": "SCO 42, Sector 44C, Sector 44",
    "area": "Sector 44",
    "city": "Chandigarh",
    "website": "N",
    "phone": "+91 172 493 4444",
    "latitude": 30.7088,
    "longitude": 76.7412,
    "hours": "11:00 AM - 10:30 PM"
  },
  {
    "name": "L'Opera Elante",
    "category": "Bakery Cafe",
    "rating": 4.4,
    "reviews": 320,
    "address": "Elante Mall, Phase 1, Industrial Area",
    "area": "Elante Mall",
    "city": "Chandigarh",
    "website": "Y",
    "phone": "+91 172 494 5555",
    "latitude": 30.7061,
    "longitude": 76.8018,
    "hours": "10:00 AM - 11:00 PM"
  },
  {
    "name": "GupShup Cafe Mohali",
    "category": "Book Cafe",
    "rating": 4.4,
    "reviews": 110,
    "address": "Sector 70",
    "area": "Sector 70",
    "city": "Mohali",
    "website": "N",
    "phone": "+91 172 495 6666",
    "latitude": 30.6912,
    "longitude": 76.7118,
    "hours": "11:00 AM - 11:00 PM"
  },
  {
    "name": "The Coffee Collective",
    "category": "Coffee Shop",
    "rating": 4.6,
    "reviews": 240,
    "address": "Phase 10",
    "area": "Phase 10",
    "city": "Mohali",
    "website": "N",
    "phone": "+91 172 496 7777",
    "latitude": 30.6808,
    "longitude": 76.7354,
    "hours": "9:00 AM - 10:30 PM"
  },
  {
    "name": "Sector 35 Coffee Bean",
    "category": "Coffee Shop",
    "rating": 4.3,
    "reviews": 980,
    "address": "SCO 445, Sector 35C, Sector 35",
    "area": "Sector 35",
    "city": "Chandigarh",
    "website": "Y",
    "phone": "+91 172 497 8888",
    "latitude": 30.7226,
    "longitude": 76.7683,
    "hours": "9:00 AM - 11:30 PM"
  },
  {
    "name": "DND - Daily Nutritional Diet",
    "category": "Bistro",
    "rating": 4.2,
    "reviews": 380,
    "address": "SCO 112, Sector 34C, Sector 34",
    "area": "Sector 34",
    "city": "Chandigarh",
    "website": "Y",
    "phone": "+91 172 498 9999",
    "latitude": 30.7185,
    "longitude": 76.7608,
    "hours": "10:00 AM - 10:30 PM"
  },
  {
    "name": "Waffles & Co Mohali",
    "category": "Dessert Cafe",
    "rating": 4.1,
    "reviews": 120,
    "address": "Phase 3B2",
    "area": "Phase 3B2",
    "city": "Mohali",
    "website": "N",
    "phone": "",
    "latitude": 30.7032,
    "longitude": 76.7221,
    "hours": "11:00 AM - 11:00 PM"
  },
  {
    "name": "The Coffee Club",
    "category": "Coffee Shop",
    "rating": 4.3,
    "reviews": 110,
    "address": "Sector 8C",
    "area": "Sector 8",
    "city": "Chandigarh",
    "website": "N",
    "phone": "",
    "latitude": 30.7486,
    "longitude": 76.7989,
    "hours": "9:00 AM - 10:00 PM"
  },
  {
    "name": "Elysian Bistro",
    "category": "Bistro",
    "rating": 4.5,
    "reviews": 85,
    "address": "Sector 9D",
    "area": "Sector 9",
    "city": "Chandigarh",
    "website": "N",
    "phone": "+91 172 501 1111",
    "latitude": 30.7451,
    "longitude": 76.7941,
    "hours": "11:00 AM - 11:00 PM"
  },
  {
    "name": "Rustic Baker",
    "category": "Bakery Cafe",
    "rating": 4.4,
    "reviews": 95,
    "address": "Sector 34C",
    "area": "Sector 34",
    "city": "Chandigarh",
    "website": "N",
    "phone": "+91 172 502 2222",
    "latitude": 30.7181,
    "longitude": 76.7605,
    "hours": "9:00 AM - 10:00 PM"
  },
  {
    "name": "Chaayos Sector 35",
    "category": "Coffee Shop",
    "rating": 4.2,
    "reviews": 1950,
    "address": "SCO 449, Sector 35C, Sector 35",
    "area": "Sector 35",
    "city": "Chandigarh",
    "website": "Y",
    "phone": "+91 172 503 3333",
    "latitude": 30.7231,
    "longitude": 76.7689,
    "hours": "8:00 AM - Midnight"
  },
  {
    "name": "Kullhad Chai Mohali",
    "category": "Traditional Cafe",
    "rating": 4.0,
    "reviews": 850,
    "address": "Sector 70",
    "area": "Sector 70",
    "city": "Mohali",
    "website": "N",
    "phone": "+91 172 504 4444",
    "latitude": 30.6902,
    "longitude": 76.7105,
    "hours": "10:00 AM - 10:00 PM"
  },
  {
    "name": "Indian Coffee House Mohali",
    "category": "Traditional Cafe",
    "rating": 4.0,
    "reviews": 1200,
    "address": "SCF 10, Phase 3B2",
    "area": "Phase 3B2",
    "city": "Mohali",
    "website": "N",
    "phone": "+91 172 505 5555",
    "latitude": 30.7038,
    "longitude": 76.7229,
    "hours": "8:00 AM - 10:00 PM"
  },
  {
    "name": "OvenFresh Sector 35",
    "category": "Bakery Cafe",
    "rating": 4.4,
    "reviews": 5600,
    "address": "SCO 437-438, Sector 35C",
    "area": "Sector 35",
    "city": "Chandigarh",
    "website": "Y",
    "phone": "+91 172 506 1111",
    "latitude": 30.7222,
    "longitude": 76.7678,
    "hours": "9:00 AM - Midnight"
  },
  {
    "name": "OvenFresh Elante",
    "category": "Bakery Cafe",
    "rating": 4.3,
    "reviews": 4120,
    "address": "Elante Mall, Industrial Area",
    "area": "Elante Mall",
    "city": "Chandigarh",
    "website": "Y",
    "phone": "+91 172 506 2222",
    "latitude": 30.7063,
    "longitude": 76.8019,
    "hours": "11:00 AM - Midnight"
  }
]
